regex20200220/__init__.py
regex20200220/_regex20200220.cp38-win_amd64.pyd
regex20200220/_regex20200220_core.py
regex20200220/regex20200220.py
regex20200220-2020.2.20.3.dist-info/LICENSE
regex20200220-2020.2.20.3.dist-info/METADATA
regex20200220-2020.2.20.3.dist-info/WHEEL
regex20200220-2020.2.20.3.dist-info/top_level.txt
regex20200220-2020.2.20.3.dist-info/RECORD
